MergeATSClient/__init__.py
MergeATSClient/api_client.py
MergeATSClient/configuration.py
MergeATSClient/exceptions.py
MergeATSClient/model_utils.py
MergeATSClient/rest.py
MergeATSClient/api/__init__.py
MergeATSClient/api/account_details_api.py
MergeATSClient/api/account_token_api.py
MergeATSClient/api/activities_api.py
MergeATSClient/api/applications_api.py
MergeATSClient/api/attachments_api.py
MergeATSClient/api/available_actions_api.py
MergeATSClient/api/candidates_api.py
MergeATSClient/api/delete_account_api.py
MergeATSClient/api/departments_api.py
MergeATSClient/api/eeocs_api.py
MergeATSClient/api/force_resync_api.py
MergeATSClient/api/generate_key_api.py
MergeATSClient/api/interviews_api.py
MergeATSClient/api/issues_api.py
MergeATSClient/api/job_interview_stages_api.py
MergeATSClient/api/jobs_api.py
MergeATSClient/api/link_token_api.py
MergeATSClient/api/linked_accounts_api.py
MergeATSClient/api/offers_api.py
MergeATSClient/api/offices_api.py
MergeATSClient/api/passthrough_api.py
MergeATSClient/api/regenerate_key_api.py
MergeATSClient/api/reject_reasons_api.py
MergeATSClient/api/scorecards_api.py
MergeATSClient/api/sync_status_api.py
MergeATSClient/api/tags_api.py
MergeATSClient/api/users_api.py
MergeATSClient/api/webhook_receivers_api.py
MergeATSClient/apis/__init__.py
MergeATSClient/model/__init__.py
MergeATSClient/model/access_role_enum.py
MergeATSClient/model/account_details.py
MergeATSClient/model/account_details_and_actions.py
MergeATSClient/model/account_details_and_actions_integration.py
MergeATSClient/model/account_details_and_actions_status_enum.py
MergeATSClient/model/account_integration.py
MergeATSClient/model/account_token.py
MergeATSClient/model/activity.py
MergeATSClient/model/activity_type_enum.py
MergeATSClient/model/application.py
MergeATSClient/model/application_endpoint_request.py
MergeATSClient/model/application_request.py
MergeATSClient/model/application_response.py
MergeATSClient/model/application_write_model_request.py
MergeATSClient-1.3.1.dist-info/LICENSE.md
MergeATSClient-1.3.1.dist-info/METADATA
MergeATSClient-1.3.1.dist-info/WHEEL
MergeATSClient-1.3.1.dist-info/top_level.txt
MergeATSClient-1.3.1.dist-info/RECORD
