Metadata-Version: 2.1
Name: MergeATSClient
Version: 1.3.1
Summary: Merge ATS API
Home-page: 
Author: Merge Team
Author-email: hello@merge.dev
Keywords: OpenAPI,OpenAPI-Generator,Merge ATS API
Requires-Python: >=3.6
License-File: LICENSE.md
Requires-Dist: urllib3 (>=1.25.3)
Requires-Dist: python-dateutil
